rds_mysql_vectorstore/__init__.py
rds_mysql_vectorstore/vectorstore.py
langchain_volcengine_rds_mysql-0.1.0.dist-info/METADATA
langchain_volcengine_rds_mysql-0.1.0.dist-info/WHEEL
langchain_volcengine_rds_mysql-0.1.0.dist-info/top_level.txt
langchain_volcengine_rds_mysql-0.1.0.dist-info/RECORD
