Metadata-Version: 2.4
Name: langchain-volcengine-rds-mysql
Version: 0.1.0
Summary: LangChain VectorStore for VolcEngine RDS for MySQL native vector indexing (HNSW)
Author-email: Siyu Chen <chen.siyu@bytedance.com>
License: Apache-2.0
Keywords: vector store,vector database,mysql,volcengine,rds,langchain
Classifier: Development Status :: 4 - Beta
Classifier: Intended Audience :: Developers
Classifier: License :: OSI Approved :: Apache Software License
Classifier: Programming Language :: Python :: 3
Classifier: Programming Language :: Python :: 3.9
Classifier: Programming Language :: Python :: 3.10
Classifier: Programming Language :: Python :: 3.11
Classifier: Topic :: Scientific/Engineering :: Artificial Intelligence
Classifier: Topic :: Database
Requires-Python: >=3.9
Requires-Dist: langchain-core>=0.2.15
Requires-Dist: langchain-community>=0.2.15
Requires-Dist: pymysql>=1.1
Requires-Dist: typing-extensions>=3.10
